moosetools/__init__.py
moosetools/connect/__init__.py
moosetools/connect/headers.py
moosetools/connect/sessions.py
moosetools/test/__init__.py
moosetools/test/conftest.py
moosetools/test/test_connect.py
moosetools/test/test_moose.py
moosetools-0.6.2.dist-info/WHEEL
moosetools-0.6.2.dist-info/METADATA
moosetools-0.6.2.dist-info/RECORD
