Metadata-Version: 2.1
Name: moosetools
Version: 0.6.2
Summary: Moose Tools
Home-page: https://moosetools.moosejudge.com
License: LGPL-3.0-or-later
Author: Chuck Mo
Author-email: chuck@moosejudge.com
Requires-Python: >=3.6,<4.0
Classifier: License :: OSI Approved :: GNU Lesser General Public License v3 or later (LGPLv3+)
Classifier: Programming Language :: Python :: 3
Classifier: Programming Language :: Python :: 3.6
Classifier: Programming Language :: Python :: 3.7
Classifier: Programming Language :: Python :: 3.8
Classifier: Programming Language :: Python :: 3.9
Classifier: Topic :: Software Development :: Libraries :: Python Modules
Requires-Dist: requests (>=2,<3)
Requires-Dist: requests-toolbelt (>=0.9.1,<0.10.0)
Project-URL: Repository, https://github.com/TheChuckMo/moosetools
